Workbook

Sheet Synthèse
A1: Coûts opérationnels — Exincourt
A2: Généré le 2026-09-23 16:50 — ordres de grandeur À CONFIRMER (PTF RTE, devis opérateurs). Barèmes éditables dans l'onglet Hypothèses.
A4: Adresse | B4: Es Meser et Courtes Parts 25400 Exincourt
A5: Parcelles | B5: Section AD N° 0046
A6: Surface | B6: 30.28 ha
A7: Zone PLU | B7: UYb
A8: Poste HTB retenu | B8: RTE (63 kV, 0.7 km)
A9: Capacité brute estimée | B9: 500 MW
A11: Scénarios de puissance (MW IT)
A12: Scénario | B12: Densité (MW/ha/étage) | C12: Besoin (MW) | D12: Couvert par la capacité estimée ?
A13: Conservateur | B13: 5 | C13: =B13*30.280 | D13: =IF(500.0>=C13,"OUI","NON — déficit "&ROUND(C13-500.0,0)&" MW")
A14: Médian | B14: 10 | C14: =B14*30.280 | D14: =IF(500.0>=C14,"OUI","NON — déficit "&ROUND(C14-500.0,0)&" MW")
A15: Max théorique | B15: 15 | C15: =B15*30.280 | D15: =IF(500.0>=C15,"OUI","NON — déficit "&ROUND(C15-500.0,0)&" MW")
A16: Taille de projet finançable par le réseau actuel | C16: =MIN(1,500.0/C14) | D16: part du scénario médian réalisable sans renforcement
A19: Totaux estimés
A20: Poste | B20: Min | C20: Max | D20: Unité | E20: Fiab.
A21: Raccordement électrique (scénario retenu) | B21: ='Raccordement élec'!F19 | C21: ='Raccordement élec'!G19 | D21: M€ | E21: B
A22: Fibre (double adduction) | B22: ='Fibre'!F9/1000 | C22: ='Fibre'!G9/1000 | D22: M€ | E22: B
A23: Études + ICPE | B23: ='Autres postes'!B4+'Autres postes'!B5 | C23: ='Autres postes'!C4+'Autres postes'!C5 | D23: M€ | E23: C
A24: Acquisition foncière (ordre de grandeur DVF) | B24: ='Autres postes'!B6 | C24: ='Autres postes'!C6 | D24: M€ | E24: B
A25: TOTAL coût d'entrée (raccordements + démarches + foncier) | B25: =SUM(B21:B24) | C25: =SUM(C21:C24) | D25: M€ | E25: B/C
A27: Chemin critique estimé | B27: =MAX('Délais & démarches'!C:C) | C27: =MAX('Délais & démarches'!D:D) | D27: mois | E27: C
A28: Coût complet du MW installé (CAPEX + coût d'entrée) | B28: =IF('Autres postes'!B9>0,('Autres postes'!B10+B25)/'Autres postes'!B9,"n.d.") | C28: =IF('Autres postes'!B9>0,('Autres postes'!C10+C25)/'Autres postes'!B9,"n.d.") | D28: M€/MW IT (médian) — benchmark constr. ~10,4 (T&T 2026) | E28: B
A29: CAPEX détaillé : onglet 'Autres postes'.
A30: Fiabilité : A = donnée mesurée/officielle (cadastre, DVF, tracé routé) · B = barème public recalé sur des projets réels (CRE, SDDR, ADEME) · C = ordre de grandeur expert — à confirmer (PTF, devis).

Sheet Hypothèses
A1: Hypothèses & barèmes (éditables — les calculs se mettent à jour)
A2: Ordres de grandeur sourcés ; à recaler par régression sur dataset S3REnR / données internes (les feuilles référencent ces cellules).
A4: Paramètre | B4: Min | C4: Max | D4: Unité | E4: Source | F4: Date
A5: elec_ligne_63_90_kv_meur_km | B5: 0.5 | C5: 1.3 | D5: M EUR/km | E5: SDDR 2025 fiche 13 : LS 63-90 kV ~= aerien en rural ; point reel Auzouer 2025 : 1,15 M EUR/km | F5: 2026-07
A6: elec_ligne_225_kv_meur_km | B6: 1 | C6: 2.6 | D6: M EUR/km | E6: SDDR 2025 : LS 225 kV +65% vs aerien ; point reel AESC Douai 2023 : 2,54 M EUR/km | F6: 2026-07
A7: elec_ligne_400_kv_meur_km | B7: 2 | C7: 8 | D7: M EUR/km | E7: RTE : aerien 400 kV ~2.1 M EUR/km (Cotentin-Maine) ; 400 kV ~ 8x 63-90 kV | F7: 2026-07
A8: elec_poste_prive_90_meur | B8: 8 | C8: 15 | D8: M EUR | E8: Ordre de grandeur poste client 90/20 kV (a confirmer PTF) | F8: 2026-07
A9: elec_poste_prive_225_meur | B9: 15 | C9: 25 | D9: M EUR | E9: Ordre de grandeur poste client 225/20 kV (a confirmer PTF) | F9: 2026-07
A10: elec_poste_prive_400_meur | B10: 30 | C10: 60 | D10: M EUR | E10: Ordre de grandeur poste client 400 kV (a confirmer PTF) | F10: 2026-07
A11: elec_poste_coupure_meur | B11: 30 | C11: 55 | D11: M EUR | E11: Poste client en entree en coupure sur ligne HTB : DATA4 Marcoussis 33,6 M EUR audite CRE (delib. 2024-164) ; Lislet 2 (delib. 2024-163) | F11: 2026-07
A12: routing_factor_elec | B12: 1.3 | C12: 1.5 | D12: coef. | E12: Facteur de cheminement (trace reel vs vol d'oiseau) | F12: 2026-07
A13: forage_dirige_meur | B13: 0.1 | C13: 0.3 | D13: M EUR/franchissement | E13: Forage dirige par franchissement (autoroute, voie ferree, riviere) | F13: 2026-07
A14: surcout_urbain_coef | B14: 1.5 | C14: 3 | D14: coef. | E14: Surcout tranchee en zone urbaine dense vs accotement rural | F14: 2026-07
A15: fibre_gc_keur_km | B15: 15 | C15: 40 | D15: k EUR/km | E15: Genie civil fibre RURAL/accotement (10-40 EUR/ml, retours terrain) | F15: 2026-07
A16: fibre_gc_urbain_keur_km | B16: 80 | C16: 180 | D16: k EUR/km | E16: Tranchee sous chaussee : Cerema ~100-150 EUR/ml ; constate AURA 2024-2025 : 80-180 EUR/ml | F16: 2026-07
... A31: delai_plu_revision_mois | B31: 24 | C31: 48 | D31: mois | E31: Revision generale ou declaration de projet avec MECDU | F31: 2026-07

Sheet Raccordement élec
A1: Raccordement électrique HTB — estimation
A2: Poste retenu : RTE (63 kV) à 0.66 km à vol d'oiseau. Ordres de grandeur À CONFIRMER PAR PTF RTE.
A4: Poste de coût | B4: Quantité | C4: Unité | D4: Coût unit. min | E4: Coût unit. max | F4: Total min (M€) | G4: Total max (M€) | H4: Fiab.
A5: Longueur du tracé routier (routage IGN) | B5: 2.47 | C5: km | H5: A
A6: Longueur de liaison retenue (tracé suit la voirie) | B6: =B5 | C6: km
A7: Liaison souterraine 63 kV | B7: =B6 | C7: km | D7: ='Hypothèses'!B5 | E7: ='Hypothèses'!C5 | F7: =B7*D7 | G7: =B7*E7 | H7: B
A8: Poste de transformation privé (SSE client) | B8: 1 | C8: u | D8: ='Hypothèses'!B8 | E8: ='Hypothèses'!C8 | F8: =B8*D8 | G8: =B8*E8 | H8: C
A9: Franchissements en forage dirigé (autoroute / fer / eau) | B9: 7 | C9: u | D9: ='Hypothèses'!B13 | E9: ='Hypothèses'!C13 | F9: =B9*D9 | G9: =B9*E9 | H9: B
A10: TOTAL raccordement électrique | F10: =SUM(F7:F9) | G10: =SUM(G7:G9) | H10: C
A12: Hors renforcements amont du réseau (fixés par la PTF). Tracé : 1.98 km urbains / 0.49 km ruraux (surcoût urbain : voir 'surcout_urbain_coef' dans Hypothèses).
A14: SCÉNARIO B — piquage ligne 225 kV à 1.5 km (potentiel ~300 MW)
A15: Liaison site → point de piquage (x facteur cheminement) | B15: 2.09 | C15: km | D15: ='Hypothèses'!B6 | E15: ='Hypothèses'!C6 | F15: =B15*D15 | G15: =B15*E15 | H15: B
A16: Poste client en entrée en coupure (réf. DATA4 / Lislet 2) | B16: 1 | C16: u | D16: ='Hypothèses'!B11 | E16: ='Hypothèses'!C11 | F16: =B16*D16 | G16: =B16*E16 | H16: B
A17: TOTAL scénario B (piquage) | F17: =SUM(F15:F16) | G17: =SUM(G15:G16) | H17: B
A19: SCÉNARIO RETENU (coût médian minimal) | B19: =IF((F17+G17)<(F10+G10),"B — piquage","A — poste existant") | F19: =IF((F17+G17)<(F10+G10),F17,F10) | G19: =IF((F17+G17)<(F10+G10),G17,G10) | H19: B
A21: Scénario B : suppose l'accord RTE sur l'entrée en coupure (à confirmer par PTF). Coordonnées de ligne = centre du tronçon OSM — tracé et point de piquage à affiner en étude.

Sheet Fibre
A1: Raccordement fibre optique — estimation
A2: Raccordement au point de piquage sur le backbone (pas au POP Arteria (FON SNCF)) : 0.0 km routés (routage OSRM).
A4: Poste de coût | B4: Quantité | C4: Unité | D4: Coût unit. min | E4: Coût unit. max | F4: Total min (k€) | G4: Total max (k€) | H4: Fiab.
A5: Distance de raccordement (tracé routier) | B5: 0 | C5: km | H5: A
A6: Nombre d'adductions (diversité de chemins) | B6: ='Hypothèses'!B17 | C6: u
A7: Génie civil + tirage fibre | B7: =B5*B6 | C7: km | D7: ='Hypothèses'!B15 | E7: ='Hypothèses'!C15 | F7: =B7*D7 | G7: =B7*E7 | H7: B
A9: TOTAL fibre (k€) | F9: =F7 | G9: =G7 | H9: B
A11: Le 2e chemin peut réutiliser des fourreaux loués (offre régulée) — devis opérateur souvent inférieur.

Sheet Autres postes
A1: Autres postes de coûts (indicatif)
A3: Poste | B3: Min (M€) | C3: Max (M€) | D3: Commentaire
A4: Études techniques amont | B4: ='Hypothèses'!B24 | C4: ='Hypothèses'!C24 | D4: G1/G2, environnement, dangers, MOE amont | E4: C
A5: Dossier ICPE | B5: ='Hypothèses'!B25 | C5: ='Hypothèses'!C25 | D5: Rubriques 2921 / 3110 / 4802 selon configuration | E5: C
A6: Acquisition foncière (ordre de grandeur DVF) | B6: 8.9 | C6: 8.9 | D6: P25-P75 DVF (1 ventes de terrains, 2023-2023) x 30.3 ha — à remplacer par le prix négocié | E6: B
A8: CAPEX datacenter (hors raccordements) — scénario médian
A9: Puissance IT retenue (éditable) | B9: =Synthèse!C14 | C9: MW
A10: CAPEX estimé | B10: =B9*'Hypothèses'!B18 | C10: =B9*'Hypothèses'!C18 | D10: M€ (min / max) | E10: B

Sheet Délais & démarches
A1: Délais par voie (parallélisables) — chemin critique = la voie la plus longue
A3: Voie | B3: Étape | C3: Min (mois) | D3: Max (mois)
A4: Urbanisme | B4: Permis de construire | C4: ='Hypothèses'!B28 | D4: ='Hypothèses'!C28
A5: Environnement | B5: ICPE | C5: ='Hypothèses'!B29 | D5: ='Hypothèses'!C29
A6: Énergie | B6: PTF RTE | C6: ='Hypothèses'!B26 | D6: ='Hypothèses'!C26
A7: Énergie | B7: Travaux de raccordement | C7: ='Hypothèses'!B27 | D7: ='Hypothèses'!C27
A9: Voie Urbanisme (séquentielle) | C9: =SUMIF(A4:A7,"Urbanisme",C4:C7) | D9: =SUMIF(A4:A7,"Urbanisme",D4:D7)
A10: Voie Énergie (séquentielle) | C10: =SUMIF(A4:A7,"Énergie",C4:C7) | D10: =SUMIF(A4:A7,"Énergie",D4:D7)
A11: Voie Environnement | C11: =SUMIF(A4:A7,"Environnement",C4:C7) | D11: =SUMIF(A4:A7,"Environnement",D4:D7)
A12: CHEMIN CRITIQUE ESTIMÉ (mois) | C12: =MAX(C9:C11) | D12: =MAX(D9:D11)

Sheet Plan d'action
A1: Plan d'action conditionnel (généré selon les résultats de l'analyse)
A3: Priorité | B3: Action | C3: Interlocuteur | D3: Délai indicatif | E3: Déclencheur
A4: P2 - Structurant | B4: Demander une PTF RTE pour fiabiliser capacite, cout et delai de raccordement | C4: RTE (guichet raccordement) | D4: 3-6 mois (PTF) | E4: Systematique
A5: P2 - Structurant | B5: Consulter les operateurs fibre pour devis et diversite de chemins (POP Arteria (FON SNCF), ~2.0 km de raccordement) | C5: Operateurs (euNetworks, Colt, Zayo...) | D5: 2-4 mois | E5: Systematique
A6: P2 - Structurant | B6: Lancer le dossier ICPE (rubriques 2921 tours aerorefrigerantes, 4802 fluides, 3110 combustion / groupes electrogenes selon puissance) | C6: DREAL / prefecture | D6: 9-18 mois | E6: Systematique (generateurs de secours)
A7: P2 - Structurant | B7: Analyser la compatibilite avec 1 site(s) Seveso proche(s) (etude de dangers, distances d'effets) | C7: DREAL / exploitant Seveso | D7: 3-6 mois | E7: Seveso a proximite
A8: P3 - Opportunite | B8: Contacter l'exploitant du reseau de chaleur 'Réseau de Montbéliard' (0.9 km) : valorisation chaleur fatale, bonus au titre de la loi REEN / fiscalite | C8: Exploitant reseau / collectivite | D8: 3-6 mois | E8: Reseau chaleur < 5 km
A9: P3 - Opportunite | B9: Verifier le foncier : DPU en mairie, acte de propriete, servitudes privees, etude de sol G1/G2 | C9: Notaire / geometre / geotechnicien | D9: 2-4 mois | E9: Systematique
